[{"ifsc":"DLSC0000087","micr":110094008,"address":"CHANDPUR NEW DELHI  H NO 9,V P O CHANDPUR,NEAR NDPL TRANSFORMER,DELHI 110 081","city":"NEW DELHI","district":"SOUTH","state":"DELHI","bank_code":"DLSC"},{"ifsc":"DLSC0000086","micr":110094023,"address":"MAANDI NEW DELHI  H.NO.1,MAANDI VILLAGE,NEAR TELEPHONE EXCHANGE,NEW DELHI 110 047","city":"NEW DELHI","district":"NORTH WEST","state":"DELHI","bank_code":"DLSC"},{"ifsc":"DLSC0000085","micr":110094022,"address":"O 7,8 NEAR RATION OFFICE,MANGOLPURI,DELHI","city":"NEW DELHI","district":"NORTH WEST","state":"DELHI","bank_code":"DLSC"},{"ifsc":"DLSC0000084","micr":110094011,"address":"RASHID MARKET,GEETA COLONY DELHI 110092","city":"NEW DELHI","district":"EAST","state":"DELHI","bank_code":"DLSC"},{"ifsc":"DLSC0000083","micr":110094028,"address":"MAIN BUS STAND,NILOTHI,DELHI 110041","city":"NEW DELHI","district":"WEST","state":"DELHI","bank_code":"DLSC"},{"ifsc":"DLSC0000082","micr":110094029,"address":"OPP.DAYAL MARKET,SOCIETY BUILDING,ALIPUR,DELHI 36","city":"NEW DELHI","district":"NORTH","state":"DELHI","bank_code":"DLSC"},{"ifsc":"DLSC0000081","micr":110094026,"address":"VPO MADIPUR,DELHI 110063","city":"NEW DELHI","district":"WEST","state":"DELHI","bank_code":"DLSC"},{"ifsc":"DLSC0000044","micr":110094044,"address":"MAIN ROAD OPP.BUS STAND,TILANGPUR KOTLA,NEW DELHI 110043","city":"NEW DELHI","district":"SOUTH WEST","state":"DELHI","bank_code":"DLSC"},{"ifsc":"DLSC0000043","micr":110094043,"address":"VPO NANGLI POONA,NEAR PANCHAYAT GHAR,DELHI 110 036","city":"NEW DELHI","district":"NORTH","state":"DELHI","bank_code":"DLSC"},{"ifsc":"DLSC0000042","micr":110094042,"address":"MAIN HOLAMBI ROAD,KHERA KHURD,DELHI 110082","city":"NEW DELHI","district":"NORTH WEST","state":"DELHI","bank_code":"DLSC"},{"ifsc":"DLSC0000041","micr":110094041,"address":"J 21,GAMRI ROAD,WEST GHONDA,DELHI 110053","city":"NEW DELHI","district":"NORTH EAST","state":"DELHI","bank_code":"DLSC"},{"ifsc":"DLSC0000040","micr":110094040,"address":"BHUP SINGH COMPLEX,LABOUR CHOWK,SAMAYPUR VILLAGE,DELHI 110042","city":"NEW DELHI","district":"NORTH","state":"DELHI","bank_code":"DLSC"},{"ifsc":"DLSC0000039","micr":110094039,"address":"NEAR BUS STAND,GHEVRA,DELHI 110081","city":"NEW DELHI","district":"NORTH WEST","state":"DELHI","bank_code":"DLSC"},{"ifsc":"DLSC0000038","micr":110094038,"address":"150,MAIN BUS STAND,DEOLI VILLAGE,DELHI 110062","city":"NEW DELHI","district":"SOUTH","state":"DELHI","bank_code":"DLSC"},{"ifsc":"DLSC0000037","micr":110094037,"address":"MAIN BAWANA ROAD,NEAR SHRI KRISHAN MANDIR,POOTH KHURD,DELHI 110039","city":"NEW DELHI","district":"NORTH","state":"DELHI","bank_code":"DLSC"},{"ifsc":"DLSC0000036","micr":110094036,"address":"C BY O RAJINDERA PUBLIC SCHOOL,50 FOOT ROAD,NIHAL VIHAR,DELHI 110041","city":"NEW DELHI","district":"WEST","state":"DELHI","bank_code":"DLSC"},{"ifsc":"DLSC0000035","micr":110094035,"address":"657,1ST FLOOR,NEAR BUS STAND,MAIN ROAD,BURARI,DELHI 110084","city":"NEW DELHI","district":"CENTRAL","state":"DELHI","bank_code":"DLSC"},{"ifsc":"DLSC0000034","micr":110094034,"address":"C 424,MAIN 100 FOOT ROAD,NEAR DURGAPURI CHOWK,CHAJJUPUR DELHI 110032","city":"NEW DELHI","district":"SHAHDARA","state":"DELHI","bank_code":"DLSC"},{"ifsc":"DLSC0000033","micr":110094033,"address":"2047 48,F.A.M.E.BUILDING,OLD ANAJ MANDI,NARELA MANDI,DELHI 110040","city":"NEW DELHI","district":"NORTH","state":"DELHI","bank_code":"DLSC"},{"ifsc":"DLSC0000032","micr":110094032,"address":"MAIN JAGATPURI ROAD,WAZIRABAD VILLAGE,DELHI 110084","city":"NEW DELHI","district":"NORTH EAST","state":"DELHI","bank_code":"DLSC"},{"ifsc":"DLSC0000031","micr":110094031,"address":"576,MAIN MARKET,V.P.O.CHIRAG DELHI,DELHI 110017","city":"NEW DELHI","district":"SOUTH","state":"DELHI","bank_code":"DLSC"},{"ifsc":"DLSC0000030","micr":110094030,"address":"D 84,TIKONA PARK,OKHLA VILLAGE,DELHI 110025","city":"NEW DELHI","district":"SOUTH","state":"DELHI","bank_code":"DLSC"},{"ifsc":"DLSC0000029","micr":110094029,"address":"MAIN ROAD,NEAR CHOTTU RAM PUBLIC SCHOOL,BAKHTAWARPUR,DELHI 110036","city":"NEW DELHI","district":"NORTH","state":"DELHI","bank_code":"DLSC"},{"ifsc":"DLSC0000028","micr":110094028,"address":"APMC BUILDING,ADMINISTRATIVE BLOCK,CH.CHET RAM SABJI MANDI,OUTER RING ROAD,KESHOPUR,DELHI 110018","city":"NEW DELHI","district":"WEST","state":"DELHI","bank_code":"DLSC"},{"ifsc":"DLSC0000027","micr":110094027,"address":"F 398,KHAJOORI KHAS COLONY,MAIN WAZIRABAD ROAD,BHAJANPURA,GOKUL PURI,DELHI 110094","city":"NEW DELHI","district":"NORTH EAST","state":"DELHI","bank_code":"DLSC"},{"ifsc":"DLSC0000026","micr":110094026,"address":"A 3,DDA MARKET,NEAR NAVBHARAT APPTS,PASCHIM VIHAR,DELHI 110063","city":"NEW DELHI","district":"WEST","state":"DELHI","bank_code":"DLSC"},{"ifsc":"DLSC0000025","micr":110094025,"address":"MAIN BAWANA ROAD,OPP.BUS STOP,SHAHABAD DAULATPUR,DELHI 110042","city":"NEW DELHI","district":"NORTH","state":"DELHI","bank_code":"DLSC"},{"ifsc":"DLSC0000024","micr":110094024,"address":"MAIN AUCHANDI ROAD,NEAR BUS STAND,BAWANA,DELHI 110039","city":"NEW DELHI","district":"NORTH","state":"DELHI","bank_code":"DLSC"},{"ifsc":"DLSC0000023","micr":110094023,"address":"NEAR BUS STAND,MAIN KANJHAWALA ROAD,KARALA,DELHI 110081","city":"NEW DELHI","district":"NORTH WEST","state":"DELHI","bank_code":"DLSC"},{"ifsc":"DLSC0000022","micr":110094022,"address":"MAIN KHANJAWALA ROAD,GUGAN SINGH MARKET,BUDH VIHAR,DELHI 110086","city":"NEW DELHI","district":"NORTH WEST","state":"DELHI","bank_code":"DLSC"},{"ifsc":"DLSC0000021","micr":110094021,"address":"MEHTAB PRADHAN S BUILDING,MAIN SOHATI ROAD,NEAR SIR CHOTU RAM PARK,QUTABGARH,DELHI 110039","city":"NEW DELHI","district":"NORTH WEST","state":"DELHI","bank_code":"DLSC"},{"ifsc":"DLSC0000020","micr":110094020,"address":"UMDESH BHAWAN,MAIN PALAM ROAD,PALAM VILLAGE,DELHI 110045","city":"NEW DELHI","district":"SOUTH WEST","state":"DELHI","bank_code":"DLSC"},{"ifsc":"DLSC0000019","micr":110094019,"address":"DHANNA COMPLEX,RANI KHERA MORE,MAIN ROHTAK ROAD,MUNDKA,DELHI 110041","city":"NEW DELHI","district":"NORTH WEST","state":"DELHI","bank_code":"DLSC"},{"ifsc":"DLSC0000017","micr":110094017,"address":"DSIDC BUILDING,7 BY A,WEAVERS COLONY,SUNDER NAGRI,NAND NAGRI,DELHI 110093","city":"NEW DELHI","district":"SHAHDARA","state":"DELHI","bank_code":"DLSC"},{"ifsc":"DLSC0000016","micr":110094016,"address":"F 3,WEAVERS COLONY,BHARAT NAGAR,DELHI 110052","city":"NEW DELHI","district":"NORTH","state":"DELHI","bank_code":"DLSC"},{"ifsc":"DLSC0000015","micr":110094015,"address":"OPP.MTNL BUILDING,MAIN NAJAFGARH ROAD,BIJWASAN,DELHI 110061","city":"NEW DELHI","district":"SOUTH WEST","state":"DELHI","bank_code":"DLSC"},{"ifsc":"DLSC0000014","micr":110094014,"address":"KRISHNA COMPLEX,IST FLOOR,GAUSHALA ROAD,NAJAFGARH,DELHI 110043","city":"NEW DELHI","district":"SOUTH WEST","state":"DELHI","bank_code":"DLSC"},{"ifsc":"DLSC0000013","micr":110094013,"address":"MAIN ROHTAK ROAD,NEAR BUS STAND,NANGLOI,DELHI 110041","city":"NEW DELHI","district":"WEST","state":"DELHI","bank_code":"DLSC"},{"ifsc":"DLSC0000012","micr":110094012,"address":"OPP.JAT DHARAMSHALA,RAILWAY ROAD,NEAR BUS TERMINAL,NARELA,DELHI 110040","city":"NEW DELHI","district":"NORTH","state":"DELHI","bank_code":"DLSC"},{"ifsc":"DLSC0000011","micr":110094011,"address":"383 BY 10B,1ST FLOOR,MAIN ROAD,EAST AZAD NAGAR,NEAR SURYA NURSING HOME,SHAHDARA DELHI 51","city":"NEW DELHI","district":"SHAHDARA","state":"DELHI","bank_code":"DLSC"},{"ifsc":"DLSC0000010","micr":110094010,"address":"C BY O APNA BAZAR,KARAMPURA,MOTI NAGAR,DELHI 110015","city":"NEW DELHI","district":"WEST","state":"DELHI","bank_code":"DLSC"},{"ifsc":"DLSC0000009","micr":110094009,"address":"D 379,AZADPUR MANDI,AZADPUR,DELHI 110033","city":"NEW DELHI","district":"NORTH","state":"DELHI","bank_code":"DLSC"},{"ifsc":"DLSC0000008","micr":110094008,"address":"15 A,WARD NO.1,MEHRAULI,NEW DELHI 110030","city":"NEW DELHI","district":"SOUTH","state":"DELHI","bank_code":"DLSC"},{"ifsc":"DLSC0000007","micr":110094007,"address":"219,MAIN BAZAR,NEAR SHIV MANDIR,BADARPUR,NEW DELHI 110044","city":"NEW DELHI","district":"SOUTH","state":"DELHI","bank_code":"DLSC"},{"ifsc":"DLSC0000006","micr":110094006,"address":"3,SIRIFORT INST.AREA,AUGUST KRANTI MARG,HAUZ KHAS,NEW DELHI 110016","city":"NEW DELHI","district":"SOUTH","state":"DELHI","bank_code":"DLSC"},{"ifsc":"DLSC0000005","micr":110094005,"address":"1465 BY 7,GALI NO 7,KOTLA MUBARAKPUR,DELHI 110003","city":"NEW DELHI","district":"SOUTH","state":"DELHI","bank_code":"DLSC"},{"ifsc":"DLSC0000004","micr":110094004,"address":"18823,LAHORI GATE,KHARI BAOLI,DELHI 110006","city":"NEW DELHI","district":"CENTRAL","state":"DELHI","bank_code":"DLSC"},{"ifsc":"DLSC0000003","micr":110094003,"address":"15 BY 16,JANPATH LANE,JANPATH,NEW DELHI 110001","city":"NEW DELHI","district":"NEW DELHI","state":"DELHI","bank_code":"DLSC"},{"ifsc":"DLSC0000002","micr":110094002,"address":"31,NETAJI SUBHASH MARG,DARYAGANJ,NEW DELHI 110002","city":"NEW DELHI","district":"CENTRAL","state":"DELHI","bank_code":"DLSC"},{"ifsc":"DLSC0000001","micr":"NA","address":"31,NETAJI SUBHASH MARG,DARYAGANJ,NEW DELHI 110002","city":"NEW DELHI","district":"DELHI","state":"DELHI","bank_code":"DLSC"}]